Workbook

Sheet Dashboard
A1: THE SNACK CHOICE — LONDON EXPANSION
A2: Business Intelligence Dashboard
A4: KEY METRICS
A5: Number of Machines | B5: ='Startup Costs'!B2
A6: Total Upfront Investment | B6: ='Startup Costs'!D39
A7: Monthly Operating Cost | B7: ='Startup Costs'!D36
A8: Est. Monthly Revenue | B8: ='Startup Costs'!D42
A9: Est. Monthly Profit | B9: ='Startup Costs'!D43
A10: Months to Breakeven | B10: ='Startup Costs'!D44
A12: PRODUCT CATALOG SUMMARY
A13: Total Products Listed | B13: =COUNTA('Product Catalog'!B2:B200)
A14: Avg Gross Margin % | B14: =AVERAGE('Product Catalog'!I2:I200)
A15: Avg Net Margin % | B15: =AVERAGE('Product Catalog'!L2:L200)
A16: Min Net Margin % | B16: =MIN('Product Catalog'!L2:L200)
A17: Max Net Margin % | B17: =MAX('Product Catalog'!L2:L200)
A19: LOCATION PIPELINE
A20: Lead | B20: =COUNTIF('Location Tracker'!J2:J200,"Lead")
A21: Contacted | B21: =COUNTIF('Location Tracker'!J2:J200,"Contacted")
A22: Meeting Booked | B22: =COUNTIF('Location Tracker'!J2:J200,"Meeting Booked")
A23: Negotiating | B23: =COUNTIF('Location Tracker'!J2:J200,"Negotiating")
A24: Agreed | B24: =COUNTIF('Location Tracker'!J2:J200,"Agreed")
A25: Rejected | B25: =COUNTIF('Location Tracker'!J2:J200,"Rejected")
A27: MACHINES RESEARCHED
A28: Total Machines Listed | B28: =COUNTA('Machine Specs'!A2:A50)
A29: Avg Purchase Price (ex VAT) | B29: =AVERAGE('Machine Specs'!E2:E50)
A30: Min Purchase Price (ex VAT) | B30: =MIN('Machine Specs'!E2:E50)
A31: Max Purchase Price (ex VAT) | B31: =MAX('Machine Specs'!E2:E50)
A33: COMPETITORS
A34: Total Competitors Tracked | B34: =COUNTA('Competitor Analysis'!A2:A50)
A35: High Threat | B35: =COUNTIF('Competitor Analysis'!L2:L50,"High")
A36: Medium Threat | B36: =COUNTIF('Competitor Analysis'!L2:L50,"Medium")
A37: Low Threat | B37: =COUNTIF('Competitor Analysis'!L2:L50,"Low")

Sheet Product Catalog
A1: Category | B1: Product Name | C1: Brand | D1: Pack Size | E1: Wholesale Unit Cost (£) | F1: Wholesale Source | G1: Vend Price (£) | H1: Gross Margin (£) | I1: Gross Margin (%) | J1: Card Fee (£) | K1: Net Margin (£) | L1: Net Margin (%) | M1: Location Fit | N1: Notes
A2: Confectionery | B2: Mars Bar 51g | C2: Mars | D2: 48 | E2: 0.55 | F2: benchmark | G2: 1.4 | H2: =G2-E2 | I2: =(G2-E2)/G2 | J2: =G2*0.029 | K2: =H2-J2 | L2: =K2/G2 | M2: Universal | N2: Est. — benchmark range £0.45-0.65. Standard countline, top seller in UK vending.
A3: Confectionery | B3: Snickers 48g | C3: Mars | D3: 48 | E3: 0.55 | F3: benchmark | G3: 1.4 | H3: =G3-E3 | I3: =(G3-E3)/G3 | J3: =G3*0.029 | K3: =H3-J3 | L3: =K3/G3 | M3: Universal | N3: Est. — benchmark range £0.45-0.65. Strong seller, comparable to Mars.
A4: Confectionery | B4: KitKat 4 Finger 41.5g | C4: Nestle | D4: 24 | E4: 0.5 | F4: benchmark | G4: 1.3 | H4: =G4-E4 | I4: =(G4-E4)/G4 | J4: =G4*0.029 | K4: =H4-J4 | L4: =K4/G4 | M4: Universal | N4: Est. — benchmark range £0.45-0.60. Slightly lighter bar, lower wholesale than Mars/Snickers.
A5: Confectionery | B5: Twirl 43g | C5: Cadbury | D5: 48 | E5: 0.52 | F5: benchmark | G5: 1.3 | H5: =G5-E5 | I5: =(G5-E5)/G5 | J5: =G5*0.029 | K5: =H5-J5 | L5: =K5/G5 | M5: Universal | N5: Est. — benchmark range £0.45-0.60. Cadbury countline, consistent seller.
A6: Confectionery | B6: Dairy Milk 45g | C6: Cadbury | D6: 48 | E6: 0.55 | F6: benchmark | G6: 1.4 | H6: =G6-E6 | I6: =(G6-E6)/G6 | J6: =G6*0.029 | K6: =H6-J6 | L6: =K6/G6 | M6: Universal | N6: Est. — benchmark range £0.45-0.65. Flagship Cadbury bar.
A7: Confectionery | B7: Maltesers 37g | C7: Mars | D7: 25 | E7: 0.52 | F7: benchmark | G7: 1.3 | H7: =G7-E7 | I7: =(G7-E7)/G7 | J7: =G7*0.029 | K7: =H7-J7 | L7: =K7/G7 | M7: Universal | N7: Est. — benchmark range £0.45-0.60. Bag format, lighter weight.
A8: Confectionery | B8: Skittles Fruits 45g | C8: Mars | D8: 36 | E8: 0.48 | F8: benchmark | G8: 1.2 | H8: =G8-E8 | I8: =(G8-E8)/G8 | J8: =G8*0.029 | K8: =H8-J8 | L8: =K8/G8 | M8: Universal | N8: Est. — benchmark range £0.40-0.55. Sugar confectionery, lower wholesale than chocolate.
A9: Confectionery | B9: Haribo Starmix 40g | C9: Haribo | D9: 36 | E9: 0.45 | F9: benchmark | G9: 1.2 | H9: =G9-E9 | I9: =(G9-E9)/G9 | J9: =G9*0.029 | K9: =H9-J9 | L9: =K9/G9 | M9: Universal | N9: Est. — benchmark range £0.40-0.55. Grab bag format for vending.
A10: Confectionery | B10: Kinder Bueno 43g | C10: Ferrero | D10: 30 | E10: 0.6 | F10: benchmark | G10: 1.5 | H10: =G10-E10 | I10: =(G10-E10)/G10 | J10: =G10*0.029 | K10: =H10-J10 | L10: =K10/G10 | M10: Universal | N10: Est. — benchmark range £0.55-0.70. Premium countline, higher wholesale than standard bars.
A11: Confectionery | B11: Bounty 57g | C11: Mars | D11: 24 | E11: 0.55 | F11: benchmark | G11: 1.4 | H11: =G11-E11 | I11: =(G11-E11)/G11 | J11: =G11*0.029 | K11: =H11-J11 | L11: =K11/G11 | M11: Universal | N11: Est. — benchmark range £0.45-0.65. Twin bar, slightly heavier.
A12: Crisps | B12: Walkers Cheese & Onion Grab Bag 45g | C12: Walkers | D12: 32 | E12: 0.48 | F12: JJ Food Service | G12: 1.2 | H12: =G12-E12 | I12: =(G12-E12)/G12 | J12: =G12*0.029 | K12: =H12-J12 | L12: =K12/G12 | M12: Universal | N12: Confirmed — JJ Food Service from £15.49/case of 32 (£0.48/bag collection price, 20+ cases). Standard delivery £20.99/case (£0.66/bag). Grab bag format essential for vending.
A13: Crisps | B13: Walkers Ready Salted Grab Bag 45g | C13: Walkers | D13: 32 | E13: 0.48 | F13: JJ Food Service | G13: 1.2 | H13: =G13-E13 | I13: =(G13-E13)/G13 | J13: =G13*0.029 | K13: =H13-J13 | L13: =K13/G13 | M13: Universal | N13: Confirmed — JJ Food Service from £15.49/case of 32 (£0.48/bag collection price, 20+ cases). Second most popular Walkers flavour.
... A46: Hot Drinks | B46: Options Hot Chocolate (per cup) | C46: Options | D46: 825g tin (~33 cups) | E46: 0.14 | F46: benchmark | G46: 1.2 | H46: =G46-E46 | I46: =(G46-E46)/G46 | J46: =G46*0.029 | K46: =H46-J46 | L46: =K46/G46 | M46: Office | N46: Est. — benchmark range £0.10-0.18 per cup. Low-calorie hot choc, appeals to health-conscious. Higher per-cup cost due to smaller tins.
H47: =IF(G47="","",G47-E47) | I47: =IF(G47="","",((G47-E47)/G47)) | J47: =IF(G47="","",G47*0.029) | K47: =IF(H47="","",H47-J47) | L47: =IF(K47="","",K47/G47)
H48: =IF(G48="","",G48-E48) | I48: =IF(G48="","",((G48-E48)/G48)) | J48: =IF(G48="","",G48*0.029) | K48: =IF(H48="","",H48-J48) | L48: =IF(K48="","",K48/G48)
H49: =IF(G49="","",G49-E49) | I49: =IF(G49="","",((G49-E49)/G49)) | J49: =IF(G49="","",G49*0.029) | K49: =IF(H49="","",H49-J49) | L49: =IF(K49="","",K49/G49)
H50: =IF(G50="","",G50-E50) | I50: =IF(G50="","",((G50-E50)/G50)) | J50: =IF(G50="","",G50*0.029) | K50: =IF(H50="","",H50-J50) | L50: =IF(K50="","",K50/G50)
H51: =IF(G51="","",G51-E51) | I51: =IF(G51="","",((G51-E51)/G51)) | J51: =IF(G51="","",G51*0.029) | K51: =IF(H51="","",H51-J51) | L51: =IF(K51="","",K51/G51)
H52: =IF(G52="","",G52-E52) | I52: =IF(G52="","",((G52-E52)/G52)) | J52: =IF(G52="","",G52*0.029) | K52: =IF(H52="","",H52-J52) | L52: =IF(K52="","",K52/G52)
H53: =IF(G53="","",G53-E53) | I53: =IF(G53="","",((G53-E53)/G53)) | J53: =IF(G53="","",G53*0.029) | K53: =IF(H53="","",H53-J53) | L53: =IF(K53="","",K53/G53)
H54: =IF(G54="","",G54-E54) | I54: =IF(G54="","",((G54-E54)/G54)) | J54: =IF(G54="","",G54*0.029) | K54: =IF(H54="","",H54-J54) | L54: =IF(K54="","",K54/G54)
H55: =IF(G55="","",G55-E55) | I55: =IF(G55="","",((G55-E55)/G55)) | J55: =IF(G55="","",G55*0.029) | K55: =IF(H55="","",H55-J55) | L55: =IF(K55="","",K55/G55)
H56: =IF(G56="","",G56-E56) | I56: =IF(G56="","",((G56-E56)/G56)) | J56: =IF(G56="","",G56*0.029) | K56: =IF(H56="","",H56-J56) | L56: =IF(K56="","",K56/G56)
H57: =IF(G57="","",G57-E57) | I57: =IF(G57="","",((G57-E57)/G57)) | J57: =IF(G57="","",G57*0.029) | K57: =IF(H57="","",H57-J57) | L57: =IF(K57="","",K57/G57)
H58: =IF(G58="","",G58-E58) | I58: =IF(G58="","",((G58-E58)/G58)) | J58: =IF(G58="","",G58*0.029) | K58: =IF(H58="","",H58-J58) | L58: =IF(K58="","",K58/G58)
... H61: =IF(G61="","",G61-E61) | I61: =IF(G61="","",((G61-E61)/G61)) | J61: =IF(G61="","",G61*0.029) | K61: =IF(H61="","",H61-J61) | L61: =IF(K61="","",K61/G61)

Sheet Machine Specs
A1: Machine Name | B1: Manufacturer | C1: Type | D1: Condition | E1: Purchase Price (£) | F1: VAT (£) | G1: Total Price (£) | H1: Lease Price (£/month) | I1: Capacity (selections) | J1: Payment Systems | K1: Cashless Ready | L1: Telemetry Built-in | M1: Energy Rating | N1: Dimensions (W×D×H cm) | O1: Weight (kg) | P1: Refrigerated | Q1: Supplier | R1: Supplier Contact | S1: Warranty | T1: Notes
A2: Gusto Swing (Gusto 8) | B2: Necta (Evoca) | C2: Combo | D2: New | E2: 4200 | F2: =E2*0.2 | G2: =E2+F2 | I2: 390 items, 48 selections (24 snack, 8 food, 16 bottles), 7 trays | J2: Coin, note, cashless ready | K2: Retrofit Needed | L2: Yes | N2: H1830 x W900 x D830mm (approx.) | P2: Yes | Q2: Vendtrade | R2: vendtrade.co.uk | T2: HIGH confidence — confirmed Vendtrade price £4,200 ex VAT. Gusto Swing is now branded Gusto 8. Dual/triple temperature zones (0-4°C food, 8-15°C snack). Specs from Necta/Evoca site.
A3: Orchestra Combo | B3: Necta (Evoca) | C3: Combo | D3: New | E3: 4400 | F3: =E3*0.2 | G3: =E3+F3 | I3: Up to 464 items, 8 spirals max, 6 trays max | J3: Coin, note, cashless ready | K3: Retrofit Needed | L3: Yes | N3: H1830 x W900 x D790mm | O3: 300 | P3: Yes | Q3: Vendtrade | R3: vendtrade.co.uk | T3: HIGH confidence — confirmed Vendtrade price £4,400 ex VAT. Metallic frame supports up to 54kg of products. Max power 630W. Temp range 3-12°C. Specs from Necta/Evoca official site.
A4: Crane Voce | B4: Crane | C4: Coffee | D4: Refurbished | E4: 1600 | F4: =E4*0.2 | G4: =E4+F4 | I4: 12-18 selections, 600 x 7-9oz cups or 400 x 12oz cups (max 800 cups) | J4: Coin, note acceptor | K4: Retrofit Needed | L4: No | N4: H1830 x W700 x D790mm | O4: 193 | P4: No | Q4: Vendtrade | R4: vendtrade.co.uk | T4: HIGH confidence — confirmed Vendtrade price £1,600 ex VAT. Hot drinks machine with 2 ground coffees, 3 solubles, sugar, cream, milk. Specs from Crane technical manual.
A5: Bevmax 2 (incl. contactless) | B5: Crane | C5: Drink | D5: Refurbished | E5: 1600 | F5: =E5*0.2 | G5: =E5+F5 | I5: 45 selections, assorted bottle/can sizes | J5: Contactless included | K5: Yes | L5: No | N5: H1830 x W850 x D860mm | O5: 250 | P5: Yes | Q5: Vendtrade | R5: vendtrade.co.uk | T5: HIGH confidence — confirmed Vendtrade price £1,600 ex VAT. Includes contactless payment. 9-inch touchscreen with full-motion video. Specs from CPI/Crane official site.
A6: Necta Sfera | B6: Necta (Evoca) | C6: Combo | D6: Refurbished | E6: 1750 | F6: =E6*0.2 | G6: =E6+F6 | I6: Up to 48 selections, 300-500 products (3 snack trays, 2 bottle trays, 1 can tray) | J6: Coin, note acceptor | K6: Retrofit Needed | L6: No | N6: H1845 x W905 x D890mm | P6: Yes | Q6: Vendtrade | R6: vendtrade.co.uk | T6: HIGH confidence — confirmed Vendtrade price £1,750 ex VAT. Power 650W, 230V/50Hz. Double tempered glass. Remote monitoring via GSM. Specs from Necta manual.
A7: Klix Outlook (hot drinks) | B7: Klix (Lavazza Professional) | C7: Coffee | D7: Refurbished | E7: 1100 | F7: =E7*0.2 | G7: =E7+F7 | I7: 1375 cups, 16 drink selections | J7: Coin | K7: Retrofit Needed | L7: No | N7: H1830 x W630 x D700mm | O7: 115 | P7: No | Q7: Vendtrade | R7: vendtrade.co.uk | T7: HIGH confidence — confirmed Vendtrade price £1,100 ex VAT. In-cup technology — one-touch operation. 115kg hot-only, 132kg hot/cold variant. Weight shown is hot-only.
A8: Crane Shopper 2 | B8: Crane | C8: Snack | D8: Refurbished | E8: 2500 | F8: =E8*0.2 | G8: =E8+F8 | I8: Up to 225 products, 9 rotating shelves with individual compartments | J8: Coin, note acceptor | K8: Retrofit Needed | L8: No | N8: H1830 x W968 x D782mm | O8: 323 | P8: Yes | Q8: Vendtrade | R8: vendtrade.co.uk | T8: HIGH confidence — confirmed Vendtrade price £2,500 ex VAT. Fresh food rotating drum machine. 9 levels with 127mm vend doors. 220/240V AC. Specs from Lavazza Pro UK.
A9: Crane BevMax | B9: Crane | C9: Drink | D9: Refurbished | E9: 1100 | F9: =E9*0.2 | G9: =E9+F9 | I9: 35-45 selections, 405 x 12oz cans or 360 x 16-20oz bottles | J9: Coin, note acceptor | K9: Retrofit Needed | L9: No | N9: H1830 x W1194 x D813mm (47" wide model) | O9: 347 | P9: Yes | Q9: Vendtrade | R9: vendtrade.co.uk | T9: HIGH confidence — confirmed Vendtrade price £1,100 ex VAT. Original BevMax Classic. 5 trays. Specs from CPI/Crane official site (converted from imperial).
A10: Crane Evolution | B10: Crane | C10: Coffee | D10: Refurbished | E10: 1250 | F10: =E10*0.2 | G10: =E10+F10 | I10: ~600 x 7oz cups, hot/cold/hot water from 3 dispense positions | J10: Coin, note acceptor | K10: Retrofit Needed | L10: No | N10: H1860 x W990 x D813mm | P10: No | Q10: Vendtrade | R10: vendtrade.co.uk | T10: HIGH confidence — confirmed Vendtrade price £1,250 ex VAT. Paperless double brewer for fresh coffee/tea. Adjustable sugar and flavour levels. Specs from Vending2Go.
A11: Crane Focus | B11: Crane | C11: Snack | D11: Refurbished | E11: 1400 | F11: =E11*0.2 | G11: =E11+F11 | I11: 32 or 40 selections (Focus 32 / Focus 40 models) | J11: Coin, note acceptor | K11: Retrofit Needed | L11: No | N11: H1830 x W812-968 x D724mm (compact to standard) | O11: 237 | P11: Yes | Q11: Vendtrade | R11: vendtrade.co.uk | T11: HIGH confidence — confirmed Vendtrade price £1,400 ex VAT. SureVend delivery sensor standard. Shelves tilt to 45° for easy loading. Weight 237kg (compact) / 304kg (standard). Specs from multiple UK vendor sites.
A12: Azkoyen Palma+ H70 | B12: Azkoyen | C12: Combo | D12: Refurbished | E12: 1500 | F12: =E12*0.2 | G12: =E12+F12 | I12: 24 selections, 5 trays | J12: Coin, note acceptor | K12: Retrofit Needed | L12: No | N12: H1830 x W723 x D840mm | O12: 270 | P12: Yes | Q12: Vendtrade | R12: vendtrade.co.uk | T12: HIGH confidence — confirmed Vendtrade price £1,500 ex VAT. Compact machine. Interior temp 3°C guaranteed at 32°C/65% humidity exterior. 500W, 230V/50Hz. Double toughened glass, LED lighting. Specs from Azkoyen Vending official site.
A13: Crane Climate | B13: Crane | C13: Combo | D13: Refurbished | E13: 1750 | F13: =E13*0.2 | G13: =E13+F13 | I13: 297-312 items, 20-36 selections (snack + bottle + optional food trays) | J13: Coin, note acceptor | K13: Retrofit Needed | L13: No | N13: H1830 x W968 x D1010mm | P13: Yes | Q13: Vendtrade | R13: vendtrade.co.uk | T13: HIGH confidence — confirmed Vendtrade price £1,750 ex VAT. Dual temperature with adjustable divider separating perishable from non-perishable. Available in 20/16 and 15/5/16 configs. Specs from Vendtrade product page.
A14: SandenVendo G-Snack (with Elevator + Fridge) | B14: SandenVendo | C14: Snack | D14: Refurbished | E14: 3602 | F14: =E14*0.2 | G14: =E14+F14 | I14: Dual temperature zones for perishable and non-perishable | J14: Coin, note acceptor | K14: Retrofit Needed | L14: No | N14: H1830 x W990 x D860mm | O14: 310 | P14: Yes | Q14: Intelligent Vending Ltd | R14: intelligentvending.co.uk | T14: MEDIUM confidence — ex-showroom price £3,602 ex VAT from Intelligent Vending (never field-installed, used for demos/testing). Patented coupling system, innovative elevator, double tempered glass. Specs from product listing.
A15: Nayax VPOS Touch | B15: Nayax | C15: Other | D15: New | E15: 450 | F15: =E15*0.2 | G15: =E15+F15 | J15: Contactless, Chip & PIN, Apple Pay, Google Pay | K15: Yes | L15: Yes | P15: No | Q15: Nayax / Breaktime Solutions | R15: shop.nayax.com/uk_en/ | T15: Cashless payment terminal. £10/month subscription + 2.95% per transaction. Confirmed price from Breaktime Solutions.
F16: =IF(E16="","",E16*0.2) | G16: =IF(E16="","",E16+F16)
F17: =IF(E17="","",E17*0.2) | G17: =IF(E17="","",E17+F17)
F18: =IF(E18="","",E18*0.2) | G18: =IF(E18="","",E18+F18)
F19: =IF(E19="","",E19*0.2) | G19: =IF(E19="","",E19+F19)
F20: =IF(E20="","",E20*0.2) | G20: =IF(E20="","",E20+F20)
F21: =IF(E21="","",E21*0.2) | G21: =IF(E21="","",E21+F21)
F22: =IF(E22="","",E22*0.2) | G22: =IF(E22="","",E22+F22)
F23: =IF(E23="","",E23*0.2) | G23: =IF(E23="","",E23+F23)
F24: =IF(E24="","",E24*0.2) | G24: =IF(E24="","",E24+F24)
F25: =IF(E25="","",E25*0.2) | G25: =IF(E25="","",E25+F25)
F26: =IF(E26="","",E26*0.2) | G26: =IF(E26="","",E26+F26)
F27: =IF(E27="","",E27*0.2) | G27: =IF(E27="","",E27+F27)
... F29: =IF(E29="","",E29*0.2) | G29: =IF(E29="","",E29+F29)

Sheet Supplier Directory
A1: Supplier Name | B1: Category | C1: Products/Services | D1: Website | E1: Phone | F1: Email | G1: Location | H1: Account Required | I1: Minimum Order | J1: Delivery | K1: Payment Terms | L1: Notes
A2: Booker | B2: Wholesaler | C2: Full range grocery, snacks, drinks, confectionery, tobacco | D2: booker.co.uk | G2: 190+ branches nationwide | H2: Trade Account Only | I2: None | J2: Cash & carry or delivery from branch | K2: Pay on collection or account terms | L2: Free trade account but requires in-person registration with 2 proofs of business. Tesco-owned. Largest UK wholesaler.
A3: Bestway | B3: Wholesaler | C3: Full range grocery, snacks, drinks, confectionery, household | D3: bestway.co.uk | G3: 70 depots nationwide | H3: Yes | I3: None | J3: Delivered + collect from depot | K3: Pay on collection or account terms | L3: Free online registration. Second largest UK wholesaler.
A4: JJ Food Service | B4: Wholesaler | C4: Food service, snacks, drinks, catering supplies | D4: jjfoodservice.com | G4: Nationwide delivery | H4: No | I4: £129 for free delivery (£3 charge under) | J4: Next-day delivery | K4: Pay online at order | L4: Open to all, no membership required. Good for top-up orders and specialist lines.
A5: Hancocks | B5: Wholesaler | C5: Confectionery specialist — sweets, chocolate, snack bars | D5: hancocks.co.uk | G5: 14 stores for click-and-collect | H5: No | I5: £250 for free delivery | J5: Free delivery over £250, click-and-collect available | K5: Pay online at order | L5: Confectionery specialist. Useful for stocking chocolate/sweet vending lines at wholesale prices.
A6: Costco Business | B6: Wholesaler | C6: Bulk grocery, snacks, drinks, sundries | D6: costco.co.uk | G6: 29 UK warehouses | H6: Yes | I6: None | J6: Cash & carry only (some online delivery) | K6: Membership ~£28/year ex VAT, pay at till | L6: Good for bulk buying popular brands at competitive prices. Limited SKU range but strong on volume lines.
A7: Vending Superstore | B7: Vending Supplies | C7: 1500+ vending-specific lines — cups, lids, ingredients, spare parts, snacks | D7: vendingsuperstore.co.uk | E7: 01773 252052 | G7: Online with UK delivery | H7: No | I7: £79 for free shipping | J7: Free shipping over £79 | K7: Pay online at order | L7: Specialist vending supplier. Essential for consumables, cups, ingredients that general wholesalers don't stock.
A8: CEMA Refreshments | B8: Other | C8: Vending machine supply, installation, wholesale ingredients | D8: cemarefreshments.co.uk | G8: East Midlands | H8: No | I8: Contact for details | J8: Contact for details | K8: Contact for details | L8: Machine supplier/operator that also offers wholesale ingredients. Dual role as potential partner or supplier.
A9: Vendtrade | B9: Machine Supplier | C9: Refurbished vending machines — snack, drink, combination, coffee | D9: vendtrade.co.uk | E9: 0208 617 1212 | F9: sales@vendtrade.co.uk | G9: London area | H9: No | I9: N/A | J9: UK delivery available | K9: Contact for quote | L9: UK's largest refurbished vending machine supplier. Good entry point for lower-cost machines.
A10: V4 Vending | B10: Machine Supplier | C10: New and refurbished vending machines | D10: v4vending.co.uk | E10: 0800 0260461 | G10: UK | H10: No | I10: N/A | J10: UK delivery available | K10: Contact for quote
A11: Monkey Vend | B11: Machine Supplier | C11: Vending machines — new and refurbished | D11: monkeyvend.co.uk | G11: UK | H11: No | I11: N/A | J11: UK delivery available | K11: Contact for quote
A12: Maix Vending | B12: Machine Supplier | C12: Vending machines — new and refurbished | D12: maixvending.co.uk | G12: UK | H12: No | I12: N/A | J12: UK delivery available | K12: Contact for quote
A13: Intelligent Vending | B13: Machine Supplier | C13: Custom/smart vending machines, parts, payment peripherals, Quros IoT software platform, consultancy | D13: intelligentvending.co.uk | E13: +44 (0) 1629 825555 | G13: Black Rocks Business Park, Derbyshire | H13: No | I13: N/A | J13: UK and international | K13: Quote-based | L13: UK B2B solutions provider for automated retail. Proprietary Quros IoT platform. Made in Britain member. Specialises in secure intelligent distribution, retail, and marketing solutions. Also sells spare parts and consumables online.
A14: Nayax | B14: Payment Systems | C14: VPOS Touch cashless payment terminal, telemetry, management software | D14: nayax.com | G14: Global (Israel HQ, UK active) | H14: Yes | I14: N/A | J14: N/A | K14: VPOS Touch ~£450+VAT hardware, £10/month SaaS, 2.95% per transaction | L14: Market leader in cashless vending payments. VPOS Touch supports contactless, Apple Pay, Google Pay. Cloud management dashboard included.
A15: Payter | B15: Payment Systems | C15: Cashless payment terminals for vending and unattended retail | D15: payter.com | G15: Netherlands (UK active) | H15: Yes | I15: N/A | J15: N/A | K15: Quote-based pricing | L15: Netherlands-based, active in UK market. Alternative to Nayax. Contact for bespoke pricing.
A16: Cantaloupe | B16: Payment Systems | C16: Cashless payment terminals, telemetry, Seed management platform | D16: cantaloupe.com | G16: US HQ, UK active via distributors | H16: Yes | I16: N/A | J16: Via UK distributors | K16: Contact distributor for pricing | L16: US-based, available in UK through distributor network. Seed platform for route management and telemetry.
A17: Simply Business | B17: Insurance | C17: Public liability, product liability, business equipment insurance for vending operators | D17: simplybusiness.co.uk | G17: UK-wide (online) | H17: No | I17: N/A | J17: N/A | K17: From ~£5.64/month for basic cover; vending operator comprehensive ~£300-600/year | L17: Online insurance marketplace. Quick quotes in ~7 minutes. 9/10 Feefo rating. Covers 1500+ trade types. Get quotes for £5M public liability + product liability + equipment cover.
A18: Towergate Insurance | B18: Insurance | C18: Commercial insurance — public liability, product liability, equipment, business premises | D18: towergateinsurance.co.uk | G18: UK-wide | H18: No | I18: N/A | J18: N/A | K18: Typically £400-800/year for small vending operations (quote-dependent) | L18: Established commercial insurance broker. Has handled vending machine operator claims including multi-million pound settlements. Specialist knowledge of vending sector risks. Recommended for higher-value or multi-site operations.
A19: AVA (The Vending & Automated Retail Association) | B19: Trade Association | C19: Industry body — networking, standards, lobbying, training, events | D19: the-ava.com | F19: info@the-ava.com | G19: UK | H19: Yes | I19: N/A | J19: N/A | K19: Membership cost on application | L19: UK trade association for vending and automated retail. Membership provides credibility, networking, and industry intelligence. Worth joining once established.

Sheet Competitor Analysis
A1: Operator Name | B1: Type | C1: HQ Location | D1: UK Coverage | E1: London Presence | F1: Machine Count (est.) | G1: Service Model | H1: Target Sectors | I1: Key Differentiator | J1: Pricing Model | K1: Website | L1: Threat Level | M1: Opportunity | N1: Notes
A2: Selecta UK | B2: National | C2: Zurich (UK operations) | D2: Nationwide | E2: Strong | F2: 9,000+ (via The Vending People brands) | G2: Fully managed — install, stock, maintain | H2: Corporate, public sector, leisure, transport | I2: Scale, brand partnerships (Starbucks, Coca-Cola), Foodies micro-market concept | J2: Free placement + revenue share | K2: selecta.com | L2: High | M2: Slow to serve small/medium sites. Corporate SLAs mean inflexible service. Premium pricing leaves room for competitive indie pricing. | N2: £137M turnover 2023. 3 London depots. Acquired The Vending People. Europe's largest vending operator.
A3: The Vending People | B3: National | C3: Unknown | D3: Nationwide | E3: Strong | F3: 9,000+ | G3: Fully managed | H3: Various — corporate, education, healthcare | I3: Scale and breadth of coverage | J3: Free placement + revenue share | K3: thevendingpeople.co.uk | L3: High | M3: Now part of Selecta — potential integration friction. May deprioritise smaller accounts. | N3: Acquired by Selecta. Fleet figures overlap with Selecta's.
A4: The Jar Healthy Vending | B4: Regional | C4: Chelsea, London SW3 | D4: London-centric | E4: Strong | F4: Unknown | G4: Fully managed with smart monitoring | H4: Offices, health-conscious workplaces, premium locations | I4: Healthy/premium niche, curated product range, brand identity | J4: Free placement, managed service | K4: eatjar.com | L4: Medium | M4: Narrow niche — only healthy/premium. Leaves conventional snack/drink market open. Likely premium pricing limits to affluent areas. | N4: Strong brand positioning in wellness space. Good benchmark for healthy vending differentiation.
A5: Vending Services Ltd | B5: Regional | C5: Rochester, Kent | D5: London & South East | E5: Moderate | F5: Unknown | G5: Fully managed | H5: Various | I5: 25+ years experience, local relationships | J5: Contact for quote | K5: vendingservices.co.uk | L5: Medium | M5: Kent-based — less responsive to central/north London. Established but may lack modern tech (cashless, telemetry). | N5: Contact: matthew@vendingservices.co.uk. Long-standing operator.
A6: Westways Vending | B6: Regional | C6: Reading | D6: Surrey, Sussex, Kent, South London | E6: Moderate | F6: Unknown | G6: Fully managed | H6: Various | I6: Family-owned ~50 years, deep local knowledge | J6: Contact for quote | K6: westwaysvending.co.uk | L6: Low | M6: Reading-based — south London fringe only. No central/north/east London presence. Aging business model possible. | N6: Long-established family business. Primarily M4 corridor and Home Counties.
A7: MorVend | B7: Regional | C7: London | D7: London & South East | E7: Moderate | F7: Unknown | G7: Fully managed | H7: Various | I7: Family-run since 1968, deep London knowledge | J7: Contact for quote | K7: morvend.co.uk | L7: Medium | M7: Legacy operator — may be slower to adopt cashless/telemetry tech. Potential acquisition target or partnership. | N7: Family-run since 1968. One of London's longest-running independents.
A8: Nu Vending | B8: Regional | C8: London NW10 | D8: London | E8: Strong | F8: Unknown | G8: Fully managed + micro markets | H8: Offices, hospitals, hotels | I8: Strong London focus, micro market capability | J8: Free placement, managed service | K8: nuvending.co.uk | L8: High | M8: Direct competitor in London. Differentiating on service speed, niche locations, or healthier options could carve space. | N8: London's foremost vending solutions provider. Also offers micro markets — a growing segment.
A9: The Snack Choice | B9: Independent | C9: Southampton | D9: Hampshire | E9: Weak | F9: 15+ installations | G9: Fully managed | H9: Local businesses | I9: Small, agile, personal service | J9: Contact for quote | K9: thesnackchoice.co.uk | L9: Low | M9: No London presence. Benchmark comparator — similar stage/scale to target operation. | N9: Romell/Sade's operation. Useful as peer benchmark for growth trajectory and operational model.
A10: Compass Group (Canteen) | B10: National | C10: Chertsey, Surrey (Global FM) | D10: Nationwide | E10: Strong | F10: Unknown (part of broader FM offering) | G10: Integrated facilities management including vending | H10: Large corporate, education, healthcare, defence | I10: Scale, bundled FM contracts, global brand | J10: Bundled within FM contracts | K10: compass-group.co.uk | L10: High | M10: Only serves large corporates with full FM contracts. SMEs and independents are not their market. Vending is add-on, not core focus. | N10: World's largest food service company. Vending is a small part of their offering.
A11: Aramark | B11: National | C11: Philadelphia, US (UK operations) | D11: Nationwide | E11: Moderate | F11: Unknown (part of broader FM offering) | G11: Integrated facilities management including vending | H11: Corporate, education, healthcare | I11: Global scale, bundled services | J11: Bundled within FM contracts | K11: aramark.co.uk | L11: Medium | M11: Same as Compass — locked into large FM contracts. No interest in small sites. Vending not core. | N11: US-headquartered FM giant. UK presence via corporate contracts.
A12: Sodexo | B12: National | C12: Paris (UK operations) | D12: Nationwide | E12: Moderate | F12: Unknown (part of broader FM offering) | G12: Integrated facilities management including vending | H12: Corporate, government, education, healthcare | I12: Global scale, bundled FM, strong public sector presence | J12: Bundled within FM contracts | K12: sodexo.com | L12: Medium | M12: Same pattern — large FM contracts only. Strong in public sector which is hard to crack anyway. | N12: French FM giant. UK operations significant but vending is minor component.
... A15: Dupont Latour | B15: Independent | C15: London | D15: London and South East | E15: Moderate | F15: Unknown | G15: Design, build and install micro markets and food service spaces | H15: Factories, corporate offices | I15: Micro market design/build specialist, modular solutions, bespoke installations | J15: Quote-based project work | K15: dupontlatour.com | L15: Low | M15: More of a fit-out company than an operator. Could be a partner rather than competitor — they build the space, you operate it. | N15: Established 2011. Designs food service counters, cafes, restaurant interiors, and micro market installations. More fit-out than operations.

Sheet Startup Costs
A1: STARTUP COST CALCULATOR
A2: Number of machines: | B2: 2 | C2: machines
A4: CAPITAL COSTS | B4: Per Machine (£) | C4: Quantity | D4: Total (£)
A5: Vending Machine (refurb) | B5: 1750 | C5: =$B$2 | D5: =B5*C5
A6: VAT on Machine | B6: =B5*0.2 | C6: =$B$2 | D6: =B6*C6
A7: Nayax VPOS Touch | B7: 450 | C7: =$B$2 | D7: =B7*C7
A8: VAT on Nayax | B8: =B7*0.2 | C8: =$B$2 | D8: =B8*C8
A9: Delivery & Installation | B9: 150 | C9: =$B$2 | D9: =B9*C9
A10: Initial Stock Fill | B10: 200 | C10: =$B$2 | D10: =B10*C10
A11: Subtotal Capital | D11: =SUM(D5:D10)
A13: SETUP COSTS (ONE-OFF) | B13: Cost (£) | C13: Qty | D13: Total (£)
A14: Company Registration (Ltd) | B14: 50 | C14: 1 | D14: =B14*C14 | E14: Companies House
A15: Food Business Registration | B15: 0 | C15: 1 | D15: =B15*C15 | E15: Free, local council, 28 days before trading
A16: Food Hygiene Certificate | B16: 150 | C16: 1 | D16: =B16*C16 | E16: Level 2 online course
A17: Public Liability Insurance (annual) | B17: 150 | C17: 1 | D17: =B17*C17 | E17: £1-2M cover — get quotes, may be £300-600
A18: Product Liability Insurance (annual) | B18: 100 | C18: 1 | D18: =B18*C18 | E18: Often bundled with above
A19: PAT Testing | B19: 50 | C19: =$B$2 | D19: =B19*C19 | E19: Per machine
A20: Nayax KYC/Setup Fee | B20: 45 | C20: 1 | D20: =B20*C20 | E20: Per Nayax account
A21: Branding/Wrapping (optional) | B21: 200 | C21: =$B$2 | D21: =B21*C21 | E21: Custom vinyl wrap per machine
A22: Printed Materials (leaflets/cards) | B22: 75 | C22: 1 | D22: =B22*C22 | E22: For site pitching
A23: Customer Acquisition (time/fuel) | B23: 100 | C23: =$B$2 | D23: =B23*C23 | E23: £100 per placed machine — ~10 pitches per win
A24: Subtotal Setup | D24: =SUM(D14:D23)
A26: MONTHLY OPERATING COSTS | B26: Per Machine/Month (£) | D26: Total/Month (£)
A27: Nayax Monthly Fee | B27: 10 | D27: =B27*$B$2
A28: Nayax SIM/Data | B28: 5 | D28: =B28*$B$2
A29: Site Rent / Commission | B29: 100 | D29: =B29*$B$2
A30: Stock Replenishment | B30: 400 | D30: =B30*$B$2
A31: Travel/Fuel | B31: 80 | D31: =B31*$B$2
A32: Electricity (if not site-covered) | B32: 0 | D32: =B32*$B$2
A33: Maintenance/Repairs Fund | B33: 30 | D33: =B33*$B$2
A34: Accountant (pro-rata monthly) | B34: 50 | D34: =B34*$B$2
A35: Misc/Phone/Admin | B35: 20 | D35: =B35
A36: Total Monthly Opex | D36: =SUM(D27:D35)
A38: SUMMARY
A39: Total Upfront Investment | D39: =D11+D24
A40: Monthly Operating Cost | D40: =D36
A41: Est. Monthly Revenue per Machine | B41: 2000 | D41: =B41*$B$2
A42: Est. Monthly Revenue Total | D42: =D41
A43: Est. Monthly Profit | D43: =D42-D40
A44: Months to Breakeven | D44: =D39/D43

Sheet Micro-Market Costs
A1: MICRO-MARKET / HONESTY SHOP CALCULATOR
A2: Number of sites: | B2: 2 | C2: sites
A4: CAPITAL COSTS (PER SITE) | B4: Per Site (£) | C4: Quantity | D4: Total (£)
A5: Commercial Fridge (undercounter/upright) | B5: 350 | C5: =$B$2 | D5: =B5*C5 | E5: Argos/Amazon Business
A6: Shelving Unit | B6: 100 | C6: =$B$2 | D6: =B6*C6 | E6: Freestanding or wall-mounted
A7: Payment Terminal (scanner/card reader) | B7: 400 | C7: =$B$2 | D7: =B7*C7 | E7: SumUp Kiosk / Nayax / PayPoint — TBC
A8: VAT on Equipment | B8: =SUM(B5:B7)*0.2 | C8: =$B$2 | D8: =B8*C8 | E8: 20% on above
A9: Signage & Branding | B9: 100 | C9: =$B$2 | D9: =B9*C9 | E9: Price labels, branding board
A10: Initial Stock Fill | B10: 250 | C10: =$B$2 | D10: =B10*C10 | E10: Wider range than vending
A11: Subtotal Capital | D11: =SUM(D5:D10)
A13: SETUP COSTS (ONE-OFF) | B13: Cost (£) | C13: Qty | D13: Total (£)
A14: Company Registration (Ltd) | B14: 50 | C14: 1 | D14: =B14*C14 | E14: Shared with vending if same entity
A15: Food Business Registration | B15: 0 | C15: 1 | D15: =B15*C15 | E15: Free, local council
A16: Food Hygiene Certificate | B16: 150 | C16: 1 | D16: =B16*C16 | E16: Level 2 online course
A17: Public Liability Insurance (annual) | B17: 200 | C17: 1 | D17: =B17*C17 | E17: May be higher for open shelving
A18: Product Liability Insurance (annual) | B18: 100 | C18: 1 | D18: =B18*C18 | E18: Covers consumed products
A19: Printed Materials | B19: 75 | C19: 1 | D19: =B19*C19 | E19: Leaflets for site pitching
A20: Customer Acquisition (time/fuel) | B20: 100 | C20: =$B$2 | D20: =B20*C20 | E20: Per site placed
A21: Subtotal Setup | D21: =SUM(D14:D20)
A23: MONTHLY OPERATING COSTS | B23: Per Site/Month (£) | D23: Total/Month (£)
A24: Payment Terminal Fee | B24: 10 | D24: =B24*$B$2 | E24: Monthly subscription
A25: Site Rent / Commission | B25: 75 | D25: =B25*$B$2 | E25: Often lower than vending — you supply product
A26: Stock Replenishment | B26: 500 | D26: =B26*$B$2 | E26: Higher volume, wider range
A27: Shrinkage Budget (3-5%) | B27: =B26*0.04 | D27: =B27*$B$2 | E27: =stock * shrinkage rate
A28: Travel/Fuel | B28: 60 | D28: =B28*$B$2 | E28: Faster restock = fewer visits
A29: Waste/Spoilage (fresh food) | B29: 30 | D29: =B29*$B$2 | E29: Set to 0 if no fresh items
A30: Accountant (pro-rata monthly) | B30: 50 | D30: =B30 | E30: Shared with vending if same entity
A31: Misc/Phone/Admin | B31: 20 | D31: =B31
A32: Total Monthly Opex | D32: =SUM(D24:D31)
A34: SUMMARY
A35: Total Upfront Investment | D35: =D11+D21
A36: Monthly Operating Cost | D36: =D32
A37: Est. Monthly Revenue per Site | B37: 2500 | D37: =B37*$B$2 | E37: Higher avg basket than vending
A38: Est. Monthly Revenue Total | D38: =D37
A39: Est. Monthly Profit | D39: =D38-D36
A40: Months to Breakeven | D40: =D35/D39
A42: VS VENDING (from Startup Costs sheet)
A43: Vending: Upfront Investment | D43: ='Startup Costs'!D39
A44: Micro-Market: Upfront Investment | D44: =D35
A45: Capital Saving | D45: =D43-D44

Sheet Location Tracker
A1: Site Name | B1: Address | C1: Postcode | D1: Borough | E1: Site Type | F1: Contact Name | G1: Contact Phone | H1: Contact Email | I1: First Contact Date | J1: Status | K1: Est. Daily Footfall | L1: Existing Vending | M1: Current Provider | N1: Contract Expiry | O1: Space Available | P1: Power Supply Nearby | Q1: Proposed Deal Structure | R1: Est. Monthly Rent (£) | S1: Revenue Share (%) | T1: Est. Weekly Revenue (£) | U1: Score (1-10) | V1: Notes

Sheet Weekly P&L
A1: Machine ID:
A2: Location:
A3: Week Commencing:
A5: Day | B5: Cash Revenue (£) | C5: Card Revenue (£) | D5: Total Revenue (£) | E5: Units Sold (Cash) | F5: Units Sold (Card) | G5: Total Units | H5: Avg Vend Price (£)
A6: Monday | D6: =B6+C6 | G6: =E6+F6 | H6: =IF(G6=0,"",D6/G6)
A7: Tuesday | D7: =B7+C7 | G7: =E7+F7 | H7: =IF(G7=0,"",D7/G7)
A8: Wednesday | D8: =B8+C8 | G8: =E8+F8 | H8: =IF(G8=0,"",D8/G8)
A9: Thursday | D9: =B9+C9 | G9: =E9+F9 | H9: =IF(G9=0,"",D9/G9)
A10: Friday | D10: =B10+C10 | G10: =E10+F10 | H10: =IF(G10=0,"",D10/G10)
A11: Saturday | D11: =B11+C11 | G11: =E11+F11 | H11: =IF(G11=0,"",D11/G11)
A12: Sunday | D12: =B12+C12 | G12: =E12+F12 | H12: =IF(G12=0,"",D12/G12)
A13: WEEK TOTAL | B13: =SUM(B6:B12) | C13: =SUM(C6:C12) | D13: =SUM(D6:D12) | E13: =SUM(E6:E12) | F13: =SUM(F6:F12) | G13: =SUM(G6:G12) | H13: =IF(G13=0,"",D13/G13)
A15: COSTS | B15: Amount (£)
A16: Stock Purchased
A17: Card Processing Fees | B17: =SUM(C6:C12)*0.029
A18: Nayax Monthly (pro-rata weekly) | B18: =10/4.33
A19: Site Rent (pro-rata weekly)
A20: Travel/Fuel
A21: Other
A22: Total Costs | B22: =SUM(B16:B21)
A24: WEEKLY SUMMARY
A25: Gross Revenue | B25: =D13
A26: Total Costs | B26: =B22
A27: Net Profit | B27: =B25-B26
A28: Gross Margin % | B28: =IF(B25=0,"",(B25-B16)/B25)

Sheet Operations Log
A1: RESTOCK & VISIT LOG
A2: Date | B2: Machine/Site ID | C2: Location | D2: Visit Type | E2: Time Spent (min) | F2: Mileage | G2: Items Restocked (summary) | H2: Issues Found | I2: Cost of Stock (£)
A22: MAINTENANCE LOG
A23: Date | B23: Machine/Site ID | C23: Fault Description | D23: Severity | E23: Action Taken | F23: Parts Cost (£) | G23: Labour Cost (£) | H23: Resolved | I23: Under Warranty
A36: OPERATIONAL BELIEFS (review quarterly)
A37: Cluster density over scattered reach | D37: Add sites near existing ones. Revenue per hour of drive time is the real metric.
A38: Stock-out costs more than overstock | D38: Empty slot = lost sale + trained-away customer. Overstocked shelf = zero cost (non-perishable).
A39: Data-driven restocking, not calendar-driven | D39: Check Nayax/sales data before every run. Let demand set visit frequency, not habit.
A40: Revenue per operator-hour is the north star | D40: Track time spent per site. If a site takes 2 hours for £30/week revenue, drop it.
A41: Every visit is a gate: observe, orient, act, log | D41: Pre-visit: check dashboard. On-site: restock + inspect + clean. Post-visit: log anomalies.
A43: OPERATIONAL METHODS (review monthly)
A44: Method | B44: Current Setting | C44: Last Reviewed | D44: Notes
A45: Purchasing strategy | B45: JIT (buy morning of restock) | D45: Switch to bulk when 5+ machines
A46: Restock frequency | B46: 2x/week per machine | D46: Adjust per site based on Nayax data
A47: Product rotation cadence | B47: Monthly — swap bottom 3 sellers | D47: Track via Weekly P&L
A48: Pricing strategy | B48: 60%+ net margin target | D48: Premium sites can go higher
A49: Margin floor | B49: 30% net minimum to stock | D49: Below this, product isn't worth the slot
A50: Visit time target | B50: 30 min per machine | D50: Including travel, restock, clean
A51: Shrinkage threshold (micro-market) | B51: 5% — investigate above this | D51: Camera or format change if persistent

Sheet Performance Review
A1: PERFORMANCE REVIEW — THE ORIENTATION LOOP
A2: Fill weekly. Review monthly. Beliefs and methods evolve from what you see here.
A4: SITE PERFORMANCE (weekly)
A5: Machine/Site ID | B5: Week Commencing | C5: Revenue (£) | D5: Stock Cost (£) | E5: Gross Margin (%) | F5: Vends/Day (est.) | G5: Operator Hours | H5: Revenue per Hour (£)
E6: =IF(C6="","",(C6-D6)/C6) | H6: =IF(G6="","",C6/G6)
E7: =IF(C7="","",(C7-D7)/C7) | H7: =IF(G7="","",C7/G7)
E8: =IF(C8="","",(C8-D8)/C8) | H8: =IF(G8="","",C8/G8)
E9: =IF(C9="","",(C9-D9)/C9) | H9: =IF(G9="","",C9/G9)
E10: =IF(C10="","",(C10-D10)/C10) | H10: =IF(G10="","",C10/G10)
E11: =IF(C11="","",(C11-D11)/C11) | H11: =IF(G11="","",C11/G11)
E12: =IF(C12="","",(C12-D12)/C12) | H12: =IF(G12="","",C12/G12)
E13: =IF(C13="","",(C13-D13)/C13) | H13: =IF(G13="","",C13/G13)
E14: =IF(C14="","",(C14-D14)/C14) | H14: =IF(G14="","",C14/G14)
E15: =IF(C15="","",(C15-D15)/C15) | H15: =IF(G15="","",C15/G15)
E16: =IF(C16="","",(C16-D16)/C16) | H16: =IF(G16="","",C16/G16)
E17: =IF(C17="","",(C17-D17)/C17) | H17: =IF(G17="","",C17/G17)
... E20: =IF(C20="","",(C20-D20)/C20) | H20: =IF(G20="","",C20/G20)
A22: PRODUCT PERFORMANCE (monthly)
A23: Product | B23: Units Sold (month) | C23: Revenue (£) | D23: COGS (£) | E23: Net Margin (%) | F23: Rank | G23: Action | H23: Notes
E24: =IF(C24="","",(C24-D24)/C24)
E25: =IF(C25="","",(C25-D25)/C25)
E26: =IF(C26="","",(C26-D26)/C26)
E27: =IF(C27="","",(C27-D27)/C27)
E28: =IF(C28="","",(C28-D28)/C28)
E29: =IF(C29="","",(C29-D29)/C29)
E30: =IF(C30="","",(C30-D30)/C30)
E31: =IF(C31="","",(C31-D31)/C31)
E32: =IF(C32="","",(C32-D32)/C32)
E33: =IF(C33="","",(C33-D33)/C33)
E34: =IF(C34="","",(C34-D34)/C34)
E35: =IF(C35="","",(C35-D35)/C35)
... E43: =IF(C43="","",(C43-D43)/C43)
A45: MONTHLY REVIEW GATE — answer before making changes
A46: OBSERVE | B46: What does the data say? | D46: Which sites are above/below target? Which products moved? Which didn't?
A47: ORIENT | B47: What does this mean? | D47: Is a low-performing site a bad location or bad product mix? Is a top seller genuinely popular or just the only option?
A48: DECIDE | B48: What will you change? | D48: Add/drop products, adjust prices, change visit frequency, drop/add sites. One change at a time — otherwise you can't tell what worked.
A49: ACT | B49: Do it. Log it. | D49: Record changes in Methods table on Operations Log. Set a review date. Don't change again until you have 4 weeks of data.
A50: PROTECT | B50: What could go wrong? | D50: Will this change break something? Customer complaint risk? Stock-out risk? Cost increase?
A52: KEY RULE: One change at a time. Wait 4 weeks. Then measure.
